MANIFEST.in
README
setup.cfg
setup.py
medialog/.DS_Store
medialog/__init__.py
medialog.newsitemview.egg-info/PKG-INFO
medialog.newsitemview.egg-info/SOURCES.txt
medialog.newsitemview.egg-info/dependency_links.txt
medialog.newsitemview.egg-info/entry_points.txt
medialog.newsitemview.egg-info/namespace_packages.txt
medialog.newsitemview.egg-info/not-zip-safe
medialog.newsitemview.egg-info/requires.txt
medialog.newsitemview.egg-info/top_level.txt
medialog/newsitemview/.DS_Store
medialog/newsitemview/__init__.py
medialog/newsitemview/behavior.py
medialog/newsitemview/behaviors.zcml
medialog/newsitemview/config.py
medialog/newsitemview/configure.zcml
medialog/newsitemview/interfaces.py
medialog/newsitemview/profiles.zcml
medialog/newsitemview/schemaextender.py
medialog/newsitemview/vocabulary.py
medialog/newsitemview/browser/__init__.py
medialog/newsitemview/browser/configure.zcml
medialog/newsitemview/browser/newsitemview.pt
medialog/newsitemview/browser/newsitemview.py
medialog/newsitemview/browser/summaryview.pt
medialog/newsitemview/browser/summaryview.py
medialog/newsitemview/profiles/.DS_Store
medialog/newsitemview/profiles/default/browserlayer.xml
medialog/newsitemview/profiles/default/metadata.xml
medialog/newsitemview/profiles/default/registry.xml
medialog/newsitemview/skins/.DS_Store
medialog/newsitemview/skins/medialog_newsitemview/folder_summary_view.pt
medialog/newsitemview/skins/medialog_newsitemview/folder_summary_view.pt.metadata
medialog/newsitemview/skins/medialog_newsitemview/newsitem_view.pt
medialog/newsitemview/skins/medialog_newsitemview/newsitem_view.pt.metadata