Metadata-Version: 1.1
Name: medialog.newsitemview
Version: 0.9
Summary: Set size of image for newsitem and folder_contents
Home-page: http://products.medialog.no
Author: Grieg Medialog [Espen Moe-Nilssen]
Author-email: espen@medialog.no
License: GPL
Keywords: plone zope newsitemview
Platform: UNKNOWN
Classifier: Framework :: Plone
Classifier: Programming Language :: Python
Classifier: Topic :: Software Development :: Libraries :: Python Modules
